cfg_diag/__init__.py
cfg_diag/py.typed
cfg_diag-0.4.0.dist-info/LICENSE
cfg_diag-0.4.0.dist-info/METADATA
cfg_diag-0.4.0.dist-info/WHEEL
cfg_diag-0.4.0.dist-info/top_level.txt
cfg_diag-0.4.0.dist-info/zip-safe
cfg_diag-0.4.0.dist-info/RECORD
